<?xml version="1.0" encoding="UTF-8"?>
<objects serializationModel="Studio.02.02.00">
	<object class="AudioFile" id="{e9fe9e9c-98b9-48b7-a81a-3b3e30b06c68}">
		<property name="assetPath">
			<value>Ambience/Bluezone_BC0229_low_drone_004.wav</value>
		</property>
		<property name="isStreaming">
			<value>true</value>
		</property>
		<property name="frequencyInKHz">
			<value>44.0999985</value>
		</property>
		<property name="channelCount">
			<value>2</value>
		</property>
		<property name="length">
			<value>38.639297052154198</value>
		</property>
		<relationship name="masterAssetFolder">
			<destination>{3440b94c-5675-483d-b93c-e9346bd282c2}</destination>
		</relationship>
	</object>
</objects>
